{
"meta":{"test_sets":[],"test_metrics":[],"learn_metrics":[{"best_value":"Min","name":"RMSE"}],"launch_mode":"Train","parameters":"","iteration_count":100,"learn_sets":["learn"],"name":"experiment"},
"iterations":[
{"learn":[14.005006],"iteration":0,"passed_time":0.001968780108,"remaining_time":0.1949092307},
{"learn":[13.14441192],"iteration":1,"passed_time":0.003436740748,"remaining_time":0.1684002967},
{"learn":[12.34258257],"iteration":2,"passed_time":0.004855911296,"remaining_time":0.1570077986},
{"learn":[11.64527793],"iteration":3,"passed_time":0.005988021777,"remaining_time":0.1437125227},
{"learn":[11.02766183],"iteration":4,"passed_time":0.007700739683,"remaining_time":0.146314054},
{"learn":[10.43485794],"iteration":5,"passed_time":0.009330739847,"remaining_time":0.1461815909},
{"learn":[9.890641275],"iteration":6,"passed_time":0.01124084849,"remaining_time":0.1493427014},
{"learn":[9.492161212],"iteration":7,"passed_time":0.01302703675,"remaining_time":0.1498109226},
{"learn":[9.105082953],"iteration":8,"passed_time":0.01472243486,"remaining_time":0.1488601747},
{"learn":[8.674157135],"iteration":9,"passed_time":0.01680122342,"remaining_time":0.1512110107},
{"learn":[8.341743544],"iteration":10,"passed_time":0.01891581997,"remaining_time":0.1530461797},
{"learn":[8.049372916],"iteration":11,"passed_time":0.02069570659,"remaining_time":0.151768515},
{"learn":[7.757318612],"iteration":12,"passed_time":0.02296596839,"remaining_time":0.1536953269},
{"learn":[7.522206899],"iteration":13,"passed_time":0.02447907239,"remaining_time":0.1503714447},
{"learn":[7.297756655],"iteration":14,"passed_time":0.0259669974,"remaining_time":0.1471463186},
{"learn":[7.088359431],"iteration":15,"passed_time":0.02779460213,"remaining_time":0.1459216612},
{"learn":[6.882113791],"iteration":16,"passed_time":0.02924065232,"remaining_time":0.1427631848},
{"learn":[6.704728832],"iteration":17,"passed_time":0.03062717257,"remaining_time":0.1395237862},
{"learn":[6.563881962],"iteration":18,"passed_time":0.0321699401,"remaining_time":0.1371455341},
{"learn":[6.418790279],"iteration":19,"passed_time":0.03407050956,"remaining_time":0.1362820383},
{"learn":[6.315756953],"iteration":20,"passed_time":0.03583341201,"remaining_time":0.1348018833},
{"learn":[6.210157751],"iteration":21,"passed_time":0.03737024013,"remaining_time":0.1324944877},
{"learn":[6.115058449],"iteration":22,"passed_time":0.03970235834,"remaining_time":0.132916591},
{"learn":[6.014819884],"iteration":23,"passed_time":0.04118164991,"remaining_time":0.130408558},
{"learn":[5.93117229],"iteration":24,"passed_time":0.04261330757,"remaining_time":0.1278399227},
{"learn":[5.844857622],"iteration":25,"passed_time":0.04463350794,"remaining_time":0.1270338303},
{"learn":[5.771145213],"iteration":26,"passed_time":0.04633676181,"remaining_time":0.1252808745},
{"learn":[5.704018229],"iteration":27,"passed_time":0.04796056052,"remaining_time":0.1233271556},
{"learn":[5.665806474],"iteration":28,"passed_time":0.05018063653,"remaining_time":0.1228560412},
{"learn":[5.616500369],"iteration":29,"passed_time":0.0518139259,"remaining_time":0.1208991604},
{"learn":[5.558023666],"iteration":30,"passed_time":0.05342441002,"remaining_time":0.1189123965},
{"learn":[5.510080976],"iteration":31,"passed_time":0.05529407931,"remaining_time":0.1174999185},
{"learn":[5.468747792],"iteration":32,"passed_time":0.05687997772,"remaining_time":0.1154835911},
{"learn":[5.429275534],"iteration":33,"passed_time":0.05831356489,"remaining_time":0.1131969201},
{"learn":[5.402117324],"iteration":34,"passed_time":0.05993739398,"remaining_time":0.1113123031},
{"learn":[5.367635151],"iteration":35,"passed_time":0.06203723202,"remaining_time":0.1102884125},
{"learn":[5.345181232],"iteration":36,"passed_time":0.06419270875,"remaining_time":0.1093010987},
{"learn":[5.319151269],"iteration":37,"passed_time":0.06674079325,"remaining_time":0.1088928732},
{"learn":[5.296134146],"iteration":38,"passed_time":0.06883805717,"remaining_time":0.1076697817},
{"learn":[5.269629003],"iteration":39,"passed_time":0.07104670865,"remaining_time":0.106570063},
{"learn":[5.251147059],"iteration":40,"passed_time":0.07324958133,"remaining_time":0.1054079341},
{"learn":[5.248003302],"iteration":41,"passed_time":0.07417856673,"remaining_time":0.1024370683},
{"learn":[5.232376509],"iteration":42,"passed_time":0.07598115246,"remaining_time":0.1007192021},
{"learn":[5.213524255],"iteration":43,"passed_time":0.07788578411,"remaining_time":0.0991273616},
{"learn":[5.189691584],"iteration":44,"passed_time":0.07955632852,"remaining_time":0.09723551263},
{"learn":[5.166052198],"iteration":45,"passed_time":0.08222879582,"remaining_time":0.09652945596},
{"learn":[5.140406659],"iteration":46,"passed_time":0.08441041833,"remaining_time":0.09518621641},
{"learn":[5.118929684],"iteration":47,"passed_time":0.08669871812,"remaining_time":0.0939236113},
{"learn":[5.108792602],"iteration":48,"passed_time":0.08882522479,"remaining_time":0.09245074417},
{"learn":[5.098141225],"iteration":49,"passed_time":0.0907481903,"remaining_time":0.0907481903},
{"learn":[5.085926393],"iteration":50,"passed_time":0.092484421,"remaining_time":0.08885758096},
{"learn":[5.067816804],"iteration":51,"passed_time":0.09497613047,"remaining_time":0.08767027428},
{"learn":[5.049834901],"iteration":52,"passed_time":0.09715946081,"remaining_time":0.08616027657},
{"learn":[5.03838627],"iteration":53,"passed_time":0.1002300257,"remaining_time":0.08538113302},
{"learn":[5.033534248],"iteration":54,"passed_time":0.1024688182,"remaining_time":0.08383812395},
{"learn":[5.023726885],"iteration":55,"passed_time":0.1052631208,"remaining_time":0.08270673773},
{"learn":[5.01290392],"iteration":56,"passed_time":0.1075553181,"remaining_time":0.0811382224},
{"learn":[5.005569127],"iteration":57,"passed_time":0.1099862371,"remaining_time":0.07964520621},
{"learn":[4.989969032],"iteration":58,"passed_time":0.1120479701,"remaining_time":0.07786384366},
{"learn":[4.976762446],"iteration":59,"passed_time":0.113581592,"remaining_time":0.07572106136},
{"learn":[4.967222715],"iteration":60,"passed_time":0.1152283829,"remaining_time":0.07367060545},
{"learn":[4.954407599],"iteration":61,"passed_time":0.117166347,"remaining_time":0.07181163205},
{"learn":[4.942125056],"iteration":62,"passed_time":0.1188477014,"remaining_time":0.06979944368},
{"learn":[4.930230716],"iteration":63,"passed_time":0.1209813513,"remaining_time":0.06805201008},
{"learn":[4.921695642],"iteration":64,"passed_time":0.1230355904,"remaining_time":0.0662499333},
{"learn":[4.906405625],"iteration":65,"passed_time":0.1248642671,"remaining_time":0.0643240164},
{"learn":[4.894330248],"iteration":66,"passed_time":0.1265545583,"remaining_time":0.06233284216},
{"learn":[4.88211557],"iteration":67,"passed_time":0.1285410874,"remaining_time":0.0604899235},
{"learn":[4.877946398],"iteration":68,"passed_time":0.1301877227,"remaining_time":0.05849013629},
{"learn":[4.863182126],"iteration":69,"passed_time":0.1318274903,"remaining_time":0.05649749583},
{"learn":[4.84646533],"iteration":70,"passed_time":0.1336331886,"remaining_time":0.05458257},
{"learn":[4.838014752],"iteration":71,"passed_time":0.1353923968,"remaining_time":0.05265259874},
{"learn":[4.82981137],"iteration":72,"passed_time":0.1373278594,"remaining_time":0.05079249594},
{"learn":[4.817094767],"iteration":73,"passed_time":0.1392085421,"remaining_time":0.0489111094},
{"learn":[4.808314151],"iteration":74,"passed_time":0.140647399,"remaining_time":0.04688246635},
{"learn":[4.796235023],"iteration":75,"passed_time":0.1421582088,"remaining_time":0.04489206594},
{"learn":[4.784434534],"iteration":76,"passed_time":0.1440198423,"remaining_time":0.04301891394},
{"learn":[4.774402487],"iteration":77,"passed_time":0.1455663383,"remaining_time":0.04105717234},
{"learn":[4.76731896],"iteration":78,"passed_time":0.1470907932,"remaining_time":0.03910008428},
{"learn":[4.75934113],"iteration":79,"passed_time":0.1497064438,"remaining_time":0.03742661094},
{"learn":[4.754106378],"iteration":80,"passed_time":0.1514752067,"remaining_time":0.03553122133},
{"learn":[4.744002932],"iteration":81,"passed_time":0.1530071493,"remaining_time":0.0335869352},
{"learn":[4.731700554],"iteration":82,"passed_time":0.155118353,"remaining_time":0.03177122892},
{"learn":[4.723284153],"iteration":83,"passed_time":0.1568334268,"remaining_time":0.02987303368},
{"learn":[4.712232782],"iteration":84,"passed_time":0.1584238936,"remaining_time":0.0279571577},
{"learn":[4.703046867],"iteration":85,"passed_time":0.1603738343,"remaining_time":0.02610736837},
{"learn":[4.698601855],"iteration":86,"passed_time":0.1623605553,"remaining_time":0.02426077264},
{"learn":[4.692429407],"iteration":87,"passed_time":0.1643878288,"remaining_time":0.0224165221},
{"learn":[4.675027364],"iteration":88,"passed_time":0.1662958977,"remaining_time":0.02055342556},
{"learn":[4.662368584],"iteration":89,"passed_time":0.1681744067,"remaining_time":0.01868604519},
{"learn":[4.646206172],"iteration":90,"passed_time":0.1696152774,"remaining_time":0.01677513732},
{"learn":[4.641245848],"iteration":91,"passed_time":0.1716595616,"remaining_time":0.0149269184},
{"learn":[4.633900435],"iteration":92,"passed_time":0.1736866052,"remaining_time":0.01307318534},
{"learn":[4.624738236],"iteration":93,"passed_time":0.1755887927,"remaining_time":0.01120779528},
{"learn":[4.612798287],"iteration":94,"passed_time":0.177641195,"remaining_time":0.009349536579},
{"learn":[4.605222001],"iteration":95,"passed_time":0.1802093378,"remaining_time":0.007508722408},
{"learn":[4.601725912],"iteration":96,"passed_time":0.1835501868,"remaining_time":0.0056768099},
{"learn":[4.59722371],"iteration":97,"passed_time":0.1861165723,"remaining_time":0.003798297393},
{"learn":[4.580235665],"iteration":98,"passed_time":0.1886039118,"remaining_time":0.001905090018},
{"learn":[4.57591791],"iteration":99,"passed_time":0.190798919,"remaining_time":0}
]}